warriorselenium/__init__.py
warriorselenium/Actions/__init__.py
warriorselenium/Actions/SeleniumActions/__init__.py
warriorselenium/Actions/SeleniumActions/browser_actions.py
warriorselenium/Actions/SeleniumActions/elementlocator_actions.py
warriorselenium/Actions/SeleniumActions/elementoperation_actions.py
warriorselenium/Actions/SeleniumActions/verify_actions.py
warriorselenium/Actions/SeleniumActions/wait_actions.py
warriorselenium/ClassUtils/__init__.py
warriorselenium/ClassUtils/WSelenium/__init__.py
warriorselenium/ClassUtils/WSelenium/browser_mgmt.py
warriorselenium/ClassUtils/WSelenium/element_locator.py
warriorselenium/ClassUtils/WSelenium/element_operations.py
warriorselenium/ClassUtils/WSelenium/verify_operations.py
warriorselenium/ClassUtils/WSelenium/wait_operations.py
warriorselenium/ProductDrivers/__init__.py
warriorselenium/ProductDrivers/selenium_driver.py
warriorselenium/Utils/__init__.py
warriorselenium/Utils/list_Utils.py
warriorselenium/Utils/rest_Utils.py
warriorselenium/Utils/selenium_Utils.py
warriorselenium-1.0.0.dist-info/METADATA
warriorselenium-1.0.0.dist-info/WHEEL
warriorselenium-1.0.0.dist-info/top_level.txt
warriorselenium-1.0.0.dist-info/RECORD
